{
  "ItemId": "Fish_Piranha_Item",
  "Category": [
    "fish",
    "freshwater"
  ],
  "Name": "Piranha",
  "Description": "Don't let its size fool you; this blue-scaled devil is a legendary terror of the murky swamps. It’s got a set of razor-sharp, interlocking teeth that can strip a catch to the bone before you even finish reeling it in. They usually hunt in schools, but a lone one is just as aggressive and won't hesitate to take a chunk out of anything that splashes in its territory.",
  "FamilyId": "Serrasalmidae",
  "Rarity": "Legendary",
  "IsGlobal": false,
  "Weight": 35,
  "Size": 30,
  "Habitats": {
    "Zones": [],
    "Tiers": [],
    "Regions": [],
    "Biomes": [
      "Forest_Swamp"
    ],
    "Min_depth": 3,
    "Height": {
      "Min_y": 0,
      "Max_y": -1
    }
  },
  "Minigame_stats": {
    "Difficulty": 10,
    "Behavior": "Aggressive",
    "Stamina": 85
  },
  "Book_info": {
    "Habitat_Info": "• Emerald Wilds's Swamps",
    "Page_File_Ui": "Almanac/Fish/Pages/FishPage3.ui"
  }
}
